{
  "syllabus": [{
    "title": "新版病理生理学教学大纲（MBBS）",
    "url": "http://118.89.35.155:8080/static/course/syllabus/新版病理生理学教学大纲-MBBS.doc"
  }, {
    "title": "新版病理生理学教学大纲（八年制）",
    "url": "http://118.89.35.155:8080/static/course/syllabus/新版病理生理学教学大纲-八年制.doc"
  }, {
    "title": "新版病理生理学教学大纲（五年制）",
    "url": "http://118.89.35.155:8080/static/course/syllabus/新版病理生理学教学大纲-五年制.doc"
  }, {
    "title": "新版病理生理学教学大纲（四年制）",
    "url": "http://118.89.35.155:8080/static/course/syllabus/新版病理生理学教学大纲-四年制.doc"
  }],
  "schedule": [{
    "title": "2016年本科病生课程进度表",
    "url": "http://118.89.35.155:8080/static/course/schedule/2016年本科病生课程进度表.docx"
  }, {
    "title": "2015年本科病生课程进度表",
    "url": "http://118.89.35.155:8080/static/course/schedule/2015年本科病生课程进度表.docx"
  }, {
    "title": "2014年本科病生课程进度表",
    "url": "http://118.89.35.155:8080/static/course/schedule/2014年本科病生课程进度表.doc"
  }, {
    "title": "2013年本科病生课程进度表",
    "url": "http://118.89.35.155:8080/static/course/schedule/2013年本科病生课程进度表.doc"
  }, {
    "title": "2012年本科病生课程进度表",
    "url": "http://118.89.35.155:8080/static/course/schedule/2012年本科病生课程进度表.doc"
  }]
}
